llm_bridge/__init__.py
llm_bridge/client/__init__.py
llm_bridge/client/chat_client.py
llm_bridge/client/implementations/__init__.py
llm_bridge/client/implementations/printing_status.py
llm_bridge/client/implementations/claude/__init__.py
llm_bridge/client/implementations/claude/claude_response_handler.py
llm_bridge/client/implementations/claude/claude_token_counter.py
llm_bridge/client/implementations/claude/non_stream_claude_client.py
llm_bridge/client/implementations/claude/stream_claude_client.py
llm_bridge/client/implementations/gemini/__init__.py
llm_bridge/client/implementations/gemini/gemini_response_handler.py
llm_bridge/client/implementations/gemini/gemini_token_counter.py
llm_bridge/client/implementations/gemini/non_stream_gemini_client.py
llm_bridge/client/implementations/gemini/stream_gemini_client.py
llm_bridge/client/implementations/openai/__init__.py
llm_bridge/client/implementations/openai/non_stream_openai_client.py
llm_bridge/client/implementations/openai/non_stream_openai_responses_client.py
llm_bridge/client/implementations/openai/openai_responses_response_handler.py
llm_bridge/client/implementations/openai/openai_token_couter.py
llm_bridge/client/implementations/openai/steam_openai_responses_client.py
llm_bridge/client/implementations/openai/stream_openai_client.py
llm_bridge/client/model_client/__init__.py
llm_bridge/client/model_client/claude_client.py
llm_bridge/client/model_client/gemini_client.py
llm_bridge/client/model_client/openai_client.py
llm_bridge/logic/__init__.py
llm_bridge/logic/file_fetch.py
llm_bridge/logic/model_prices.py
llm_bridge/logic/chat_generate/__init__.py
llm_bridge/logic/chat_generate/chat_client_factory.py
llm_bridge/logic/chat_generate/chat_message_converter.py
llm_bridge/logic/chat_generate/media_processor.py
llm_bridge/logic/chat_generate/model_client_factory/__init__.py
llm_bridge/logic/chat_generate/model_client_factory/claude_client_factory.py
llm_bridge-1.15.9.dist-info/METADATA
llm_bridge-1.15.9.dist-info/WHEEL
llm_bridge-1.15.9.dist-info/licenses/LICENSE
llm_bridge-1.15.9.dist-info/RECORD
