Metadata-Version: 2.4
Name: LLM-Bridge
Version: 1.15.9
Summary: A Bridge for LLMs
Author-email: windsnow1025 <windsnow1025@gmail.com>
License-Expression: MIT
License-File: LICENSE
Keywords: ai,llm
Classifier: Framework :: FastAPI
Classifier: Programming Language :: Python :: 3
Requires-Python: >=3.12
Requires-Dist: anthropic==0.75.0
Requires-Dist: docxlatex>=1.1.1
Requires-Dist: fastapi
Requires-Dist: google-genai==1.46.0
Requires-Dist: httpx
Requires-Dist: openai==2.9.0
Requires-Dist: openpyxl
Requires-Dist: pymupdf
Requires-Dist: python-pptx
Requires-Dist: tenacity
Requires-Dist: tiktoken==0.11.0
